[
    {
        "name": "Agahnim`s Tower",
        "chest_unopened_img": "/images/items/closed_Chest.png",
        "chest_opened_img": "/images/items/open_Chest.png",
        "children": [
            {
                "name": "",
                "sections": [
                    {
                        "ref": "AT/Aganim's Tower/Room 03"
                    }
                ],
                "map_locations": [
                    {
                        "map": "AT",
                        "x": 110,
                        "y": 235,
                        "size": 8
                    }
                ]
            },
            {
                "name": "",
                "sections": [
                    {
                        "ref": "AT/Aganim's Tower/Maze Chest"
                    }
                ],
                "map_locations": [
                    {
                        "map": "AT",
                        "x": 12,
                        "y": 115,
                        "size": 8
                    }
                ]
            },
            {
                "name": "",
                "sections": [
                    {
                        "ref": "AT/Aganim's Tower/Aganim 1"
                    }
                ],
                "map_locations": [
                    {
                        "map": "AT",
                        "x": 112,
                        "y": 115,
                        "size": 8
                    }
                ]
            }
        ]
    }
]